lasso_3d/__init__.py
lasso_3d/_widget.py
lasso_3d/lasso_add_slices.py
lasso_3d/lasso_rotate_vol.py
lasso_3d/lasso_utils.py
lasso_3d/napari.yaml
lasso_3d/shapes_overwrites.py
lasso_3d/_tests/__init__.py
lasso_3d/_tests/test_widget.py
lasso_3d-0.0.1.dist-info/LICENSE
lasso_3d-0.0.1.dist-info/METADATA
lasso_3d-0.0.1.dist-info/WHEEL
lasso_3d-0.0.1.dist-info/entry_points.txt
lasso_3d-0.0.1.dist-info/top_level.txt
lasso_3d-0.0.1.dist-info/RECORD
