Metadata-Version: 2.2
Name: lasso-3d
Version: 0.0.1
Summary: 3D lasso tool to select large 3D areas
Author: Lorenz Lamm
Author-email: lorenz.lamm@gmail.com
License: 
Project-URL: Bug Tracker, https://github.com/LorenzLamm/lasso-3d/issues
Project-URL: Documentation, https://github.com/LorenzLamm/lasso-3d#README.md
Project-URL: Source Code, https://github.com/LorenzLamm/lasso-3d
Project-URL: User Support, https://github.com/LorenzLamm/lasso-3d/issues
Classifier: Development Status :: 2 - Pre-Alpha
Classifier: Framework :: napari
Classifier: Intended Audience :: Developers
Classifier: License :: OSI Approved :: BSD License
Classifier: Operating System :: OS Independent
Classifier: Programming Language :: Python
Classifier: Programming Language :: Python :: 3
Classifier: Programming Language :: Python :: 3 :: Only
Classifier: Programming Language :: Python :: 3.9
Classifier: Programming Language :: Python :: 3.10
Classifier: Programming Language :: Python :: 3.11
Classifier: Programming Language :: Python :: 3.12
Classifier: Topic :: Scientific/Engineering :: Image Processing
Requires-Python: >=3.9
License-File: LICENSE
Requires-Dist: magicgui
Requires-Dist: membrain-seg
Requires-Dist: napari-mrcfile-reader
Requires-Dist: numpy
Requires-Dist: pyqt5
Requires-Dist: qtpy
Requires-Dist: scipy
Requires-Dist: scikit-image
Provides-Extra: testing
Requires-Dist: tox; extra == "testing"
Requires-Dist: pytest; extra == "testing"
Requires-Dist: pytest-cov; extra == "testing"
Requires-Dist: pytest-qt; extra == "testing"
Requires-Dist: napari; extra == "testing"
Requires-Dist: pyqt5; extra == "testing"
